ccmap.cpython-39-x86_64-linux-gnu.so
ccmap-4.0.2.dist-info/top_level.txt
ccmap-4.0.2.dist-info/METADATA
ccmap-4.0.2.dist-info/RECORD
ccmap-4.0.2.dist-info/WHEEL
ccmap-4.0.2.dist-info/LICENSE
